setup.py
tmxlib/__init__.py
tmxlib/fileio.py
tmxlib/helpers.py
tmxlib/image.py
tmxlib/image_base.py
tmxlib/image_pil.py
tmxlib/image_png.py
tmxlib/layer.py
tmxlib/map.py
tmxlib/mapobject.py
tmxlib/terrain.py
tmxlib/tile.py
tmxlib/tileset.py
tmxlib.egg-info/PKG-INFO
tmxlib.egg-info/SOURCES.txt
tmxlib.egg-info/dependency_links.txt
tmxlib.egg-info/not-zip-safe
tmxlib.egg-info/requires.txt
tmxlib.egg-info/top_level.txt
tmxlib/compatibility/__init__.py
tmxlib/compatibility/formencode_doctest_xml_compare.py
tmxlib_test/__init__.py
tmxlib_test/test_helpers.py
tmxlib_test/test_image.py
tmxlib_test/test_tmxlib.py