Metadata-Version: 1.1
Name: tmxlib
Version: 0.2.0
Summary: Library for manipulating TMX tile maps
Home-page: http://pytmxlib.readthedocs.org
Author: Petr Viktorin
Author-email: encukou@gmail.com
License: UNKNOWN
Platform: UNKNOWN
Classifier: Development Status :: 4 - Beta
Classifier: Intended Audience :: Developers
Classifier: License :: OSI Approved :: MIT License
Classifier: Operating System :: OS Independent
Classifier: Programming Language :: Python :: 2
Classifier: Programming Language :: Python :: 2.6
Classifier: Programming Language :: Python :: 2.7
Classifier: Programming Language :: Python :: 3
Classifier: Programming Language :: Python :: 3.2
Classifier: Programming Language :: Python :: 3.3
Classifier: Topic :: Games/Entertainment
